cargo_rocker/__init__.py
cargo_rocker/cargo_rocker.py
cargo_rocker/templates/cargo_rocker_snippet.Dockerfile
cargo_rocker-0.0.3.dist-info/METADATA
cargo_rocker-0.0.3.dist-info/WHEEL
cargo_rocker-0.0.3.dist-info/entry_points.txt
cargo_rocker-0.0.3.dist-info/licenses/LICENSE
cargo_rocker-0.0.3.dist-info/RECORD
