Metadata-Version: 2.3
Name: cargo_rocker
Version: 0.0.3
Summary: A rocker extension for installing cargo in a container
Project-URL: Source, https://github.com/blooop/cargo_rocker
Project-URL: Home, https://github.com/blooop/cargo_rocker
Author-email: Austin Gregg-Smith <blooop@gmail.com>
License-Expression: MIT
License-File: LICENSE
Requires-Dist: rocker>=0.2.17
Provides-Extra: test
Requires-Dist: black<=24.10.0,>=23; extra == 'test'
Requires-Dist: coverage<=7.6.4,>=7.5.4; extra == 'test'
Requires-Dist: hypothesis<=6.115.5,>=6.104.2; extra == 'test'
Requires-Dist: pylint<=3.3.1,>=3.2.5; extra == 'test'
Requires-Dist: pytest-cov<=5.0.0,>=4.1; extra == 'test'
Requires-Dist: pytest<=8.3.3,>=7.4; extra == 'test'
Requires-Dist: ruff<=0.7.1,>=0.5.0; extra == 'test'
